LuFeixuechengJavaFangqiZhiLuFix1/README.md
LuFeixuechengJavaFangqiZhiLuFix1/__init__.py
LuFeixuechengJavaFangqiZhiLuFix1/__main__.py
LuFeixuechengJavaFangqiZhiLuFix1/file.epub
LuFeixuechengJavaFangqiZhiLuFix1/index.html
LuFeixuechengJavaFangqiZhiLuFix1/css/__init__.py
LuFeixuechengJavaFangqiZhiLuFix1/css/annotations.css
LuFeixuechengJavaFangqiZhiLuFix1/css/main.css
LuFeixuechengJavaFangqiZhiLuFix1/css/normalize.css
LuFeixuechengJavaFangqiZhiLuFix1/css/popup.css
LuFeixuechengJavaFangqiZhiLuFix1/font/__init__.py
LuFeixuechengJavaFangqiZhiLuFix1/font/fontello.eot
LuFeixuechengJavaFangqiZhiLuFix1/font/fontello.svg
LuFeixuechengJavaFangqiZhiLuFix1/font/fontello.ttf
LuFeixuechengJavaFangqiZhiLuFix1/font/fontello.woff
LuFeixuechengJavaFangqiZhiLuFix1/img/__init__.py
LuFeixuechengJavaFangqiZhiLuFix1/img/annotator-glyph-sprite.png
LuFeixuechengJavaFangqiZhiLuFix1/img/annotator-icon-sprite.png
LuFeixuechengJavaFangqiZhiLuFix1/img/apple-touch-icon.png
LuFeixuechengJavaFangqiZhiLuFix1/img/cancelfullscreen.png
LuFeixuechengJavaFangqiZhiLuFix1/img/close.png
LuFeixuechengJavaFangqiZhiLuFix1/img/fullscreen.png
LuFeixuechengJavaFangqiZhiLuFix1/img/loader.gif
LuFeixuechengJavaFangqiZhiLuFix1/img/menu-icon.png
LuFeixuechengJavaFangqiZhiLuFix1/img/save.png
LuFeixuechengJavaFangqiZhiLuFix1/img/saved.png
LuFeixuechengJavaFangqiZhiLuFix1/img/settings-s.png
LuFeixuechengJavaFangqiZhiLuFix1/img/settings.png
LuFeixuechengJavaFangqiZhiLuFix1/img/star.png
LuFeixuechengJavaFangqiZhiLuFix1/js/__init__.py
LuFeixuechengJavaFangqiZhiLuFix1/js/epub.js
LuFeixuechengJavaFangqiZhiLuFix1/js/epub.min.js
LuFeixuechengJavaFangqiZhiLuFix1/js/epub.min.map
LuFeixuechengJavaFangqiZhiLuFix1/js/hooks.min.js
LuFeixuechengJavaFangqiZhiLuFix1/js/hooks.min.map
LuFeixuechengJavaFangqiZhiLuFix1/js/reader.js
LuFeixuechengJavaFangqiZhiLuFix1/js/reader.js.map
LuFeixuechengJavaFangqiZhiLuFix1/js/reader.min.js
LuFeixuechengJavaFangqiZhiLuFix1/js/reader.min.map
LuFeixuechengJavaFangqiZhiLuFix1/js/hooks/__init__.py
lu_feixuecheng_java_fangqi_zhi_lu_fix1-2025.3.25.1.dist-info/METADATA
lu_feixuecheng_java_fangqi_zhi_lu_fix1-2025.3.25.1.dist-info/WHEEL
lu_feixuecheng_java_fangqi_zhi_lu_fix1-2025.3.25.1.dist-info/entry_points.txt
lu_feixuecheng_java_fangqi_zhi_lu_fix1-2025.3.25.1.dist-info/top_level.txt
lu_feixuecheng_java_fangqi_zhi_lu_fix1-2025.3.25.1.dist-info/RECORD
